ShizhanGroovyXilie/README.md
ShizhanGroovyXilie/__init__.py
ShizhanGroovyXilie/__main__.py
ShizhanGroovyXilie/file.epub
ShizhanGroovyXilie/index.html
ShizhanGroovyXilie/css/__init__.py
ShizhanGroovyXilie/css/annotations.css
ShizhanGroovyXilie/css/main.css
ShizhanGroovyXilie/css/normalize.css
ShizhanGroovyXilie/css/popup.css
ShizhanGroovyXilie/font/__init__.py
ShizhanGroovyXilie/font/fontello.eot
ShizhanGroovyXilie/font/fontello.svg
ShizhanGroovyXilie/font/fontello.ttf
ShizhanGroovyXilie/font/fontello.woff
ShizhanGroovyXilie/img/__init__.py
ShizhanGroovyXilie/img/annotator-glyph-sprite.png
ShizhanGroovyXilie/img/annotator-icon-sprite.png
ShizhanGroovyXilie/img/apple-touch-icon.png
ShizhanGroovyXilie/img/cancelfullscreen.png
ShizhanGroovyXilie/img/close.png
ShizhanGroovyXilie/img/fullscreen.png
ShizhanGroovyXilie/img/loader.gif
ShizhanGroovyXilie/img/menu-icon.png
ShizhanGroovyXilie/img/save.png
ShizhanGroovyXilie/img/saved.png
ShizhanGroovyXilie/img/settings-s.png
ShizhanGroovyXilie/img/settings.png
ShizhanGroovyXilie/img/star.png
ShizhanGroovyXilie/js/__init__.py
ShizhanGroovyXilie/js/epub.js
ShizhanGroovyXilie/js/epub.min.js
ShizhanGroovyXilie/js/epub.min.map
ShizhanGroovyXilie/js/hooks.min.js
ShizhanGroovyXilie/js/hooks.min.map
ShizhanGroovyXilie/js/reader.js
ShizhanGroovyXilie/js/reader.js.map
ShizhanGroovyXilie/js/reader.min.js
ShizhanGroovyXilie/js/reader.min.map
ShizhanGroovyXilie/js/hooks/__init__.py
ShizhanGroovyXilie/js/hooks/extensions/__init__.py
ShizhanGroovyXilie/js/hooks/extensions/highlight.js
ShizhanGroovyXilie/js/libs/__init__.py
ShizhanGroovyXilie/js/libs/jquery.min.js
ShizhanGroovyXilie/js/libs/localforage.min.js
ShizhanGroovyXilie/js/libs/screenfull.js
ShizhanGroovyXilie/js/libs/screenfull.min.js
ShizhanGroovyXilie/js/libs/zip.min.js
ShizhanGroovyXilie/js/plugins/__init__.py
ShizhanGroovyXilie/js/plugins/hypothesis.js
ShizhanGroovyXilie/js/plugins/search.js
shizhan_groovy_xilie-2024.3.2.0.dist-info/METADATA
shizhan_groovy_xilie-2024.3.2.0.dist-info/WHEEL
shizhan_groovy_xilie-2024.3.2.0.dist-info/entry_points.txt
shizhan_groovy_xilie-2024.3.2.0.dist-info/top_level.txt
shizhan_groovy_xilie-2024.3.2.0.dist-info/RECORD
